{
  "minecraft:recipes/decorations/crafting_table": {
    "criteria": {
      "unlock_right_away": "2025-07-08 02:36:31 +0200"
    },
    "done": true
  },
  "minecraft:adventure/adventuring_time": {
    "criteria": {
      "minecraft:river": "2025-07-15 17:50:29 +0200",
      "minecraft:forest": "2025-07-08 02:36:32 +0200",
      "minecraft:meadow": "2025-07-08 02:37:13 +0200"
    },
    "done": false
  },
  "minecraft:recipes/misc/yellow_dye_from_dandelion": {
    "criteria": {
      "has_dandelion": "2025-07-15 17:46:13 +0200"
    },
    "done": true
  },
  "DataVersion": 3465
}